ws2udp/__init__.py
ws2udp/__main__.py
ws2udp/ws2udp.py
ws2udp-0.1.7.dist-info/LICENSE
ws2udp-0.1.7.dist-info/METADATA
ws2udp-0.1.7.dist-info/WHEEL
ws2udp-0.1.7.dist-info/entry_points.txt
ws2udp-0.1.7.dist-info/top_level.txt
ws2udp-0.1.7.dist-info/RECORD
