Metadata-Version: 2.1
Name: ws2udp
Version: 0.1.7
Summary: A WebSocket to UDP proxy
Home-page: https://github.com/bgola/ws2udp
Author: Bruno Gola, additions by Thomas Grill
Author-email: me@bgo.la, gr@grrrr.org
Keywords: websockets udp osc opensoundcontrol
Classifier: Programming Language :: Python :: 3
Classifier: License :: OSI Approved :: GNU General Public License v3 or later (GPLv3+)
Classifier: Operating System :: OS Independent
Classifier: Framework :: AsyncIO
Requires-Python: >=3.7
License-File: LICENSE
Requires-Dist: websockets
